{"generation": 5, "temperature": 9.048374180359595, "spins": [[-1, 1, 1, -1, -1, -1, 1, -1, -1, 1, 1, 1, -1, -1, -1, -1, -1, -1, -1, 1], [1, 1, -1, -1, -1, 1, 1, 1, -1, -1, 1, -1, 1, 1, -1, -1, 1, -1, 1, 1], [1, 1, 1, -1, 1, -1, 1, 1, 1, -1, -1, -1, 1, -1, 1, 1, -1, -1, -1, -1], [1, -1, -1, -1, -1, -1, -1, 1, -1, 1, 1, 1, 1, 1, 1, -1, 1, 1, 1, -1], [-1, 1, -1, -1, -1, -1, 1, 1, -1, 1, 1, 1, -1, -1, -1, 1, 1, 1, -1, -1], [1, 1, -1, 1, -1, -1, 1, 1, 1, 1, 1, -1, -1, -1, -1, 1, 1, 1, 1, 1], [-1, -1, -1, 1, 1, 1, 1, 1, -1, 1, 1, -1, -1, 1, -1, 1, -1, 1, 1, 1], [-1, -1, -1, -1, -1, 1, 1, 1, -1, 1, 1, -1, -1, 1, 1, -1, 1, 1, -1, 1], [1, -1, -1, -1, -1, 1, -1, -1, 1, 1, -1, 1, -1, -1, 1, 1, 1, 1, -1, 1], [1, -1, -1, -1, -1, -1, -1, -1, -1, 1, 1, -1, 1, 1, 1, -1, -1, -1, -1, -1], [-1, 1, -1, -1, -1, -1, 1, -1, -1, 1, 1, 1, 1, 1, -1, -1, -1, -1, 1, 1], [-1, -1, 1, -1, -1, -1, 1, -1, -1, -1, -1, -1, -1, -1, 1, 1, -1, 1, 1, 1], [1, -1, -1, 1, 1, 1, 1, 1, -1, -1, 1, -1, 1, -1, -1, 1, 1, 1, 1, 1], [1, 1, 1, 1, -1, 1, 1, -1, -1, 1, -1, -1, 1, 1, 1, 1, -1, 1, -1, 1], [1, -1, -1, 1, -1, 1, -1, -1, 1, 1, 1, 1, -1, -1, -1, 1, -1, 1, -1, -1], [-1, -1, 1, -1, -1, 1, 1, 1, -1, -1, 1, 1, 1, -1, -1, -1, 1, 1, -1, 1], [-1, -1, -1, -1, 1, 1, -1, 1, 1, -1, -1, 1, 1, -1, -1, -1, 1, -1, -1, 1], [-1, -1, -1, -1, 1, -1, -1, 1, -1, -1, -1, -1, -1, -1, 1, 1, 1, 1, 1, 1], [1, -1, 1, -1, 1, -1, 1, -1, 1, -1, -1, 1, -1, -1, -1, 1, 1, -1, -1, -1], [-1, 1, 1, 1, 1, -1, -1, -1, 1, 1, -1, -1, -1, -1, -1, -1, 1, -1, -1, -1]], "phase": "Gas (Disordered)", "magnetization": 0.045}